flake8_tabs/__init__.py
flake8_tabs/blanklineck.py
flake8_tabs/categorizer.py
flake8_tabs/config.py
flake8_tabs/editorconfig.py
flake8_tabs/indentationck.py
flake8_tabs/misc.py
flake8_tabs/monkeypatch.py
flake8_tabs-2.3.2.dist-info/entry_points.txt
flake8_tabs-2.3.2.dist-info/WHEEL
flake8_tabs-2.3.2.dist-info/METADATA
flake8_tabs-2.3.2.dist-info/LICENSE.md
flake8_tabs-2.3.2.dist-info/RECORD
