Metadata-Version: 2.1
Name: flake8-tabs
Version: 2.3.2
Summary: Tab (or Spaces) indentation style checker for flake
License: LGPL-3.0-or-later
Author-email: Alexander Schlarb <alexander@ninetailed.ninja>
Requires-Python: >=3.6
Classifier: Development Status :: 4 - Beta
Classifier: Framework :: Flake8
Classifier: Intended Audience :: Developers
Classifier: License :: OSI Approved :: GNU Lesser General Public License v3 or later (LGPLv3+)
Classifier: Operating System :: OS Independent
Classifier: Programming Language :: Python :: 3
Classifier: Programming Language :: Python :: 3.6
Classifier: Programming Language :: Python :: 3.7
Classifier: Programming Language :: Python :: 3.8
Classifier: Programming Language :: Python :: 3.9
Classifier: Topic :: Software Development :: Libraries :: Python Modules
Classifier: Topic :: Software Development :: Quality Assurance
Requires-Dist: editorconfig ~= 0.12.0
Requires-Dist: flake8 ~= 3.0
Provides-Extra: doc
Requires-Dist: sphinx; extra == "doc"
Project-URL: Issue Tracker, https://gitlab.com/ntninja/flake8-tabs/issues/
Project-URL: repository, https://gitlab.com/ntninja/flake8-tabs/-/tree/master/
